{
  "type": "FeatureCollection",
  "generator": "overpass-turbo",
  "copyright": "The data included in this document is from www.openstreetmap.org. The data is made available under ODbL.",
  "timestamp": "2016-11-17T08:35:02Z",
  "features": [
    {
      "type": "Feature",
      "id": "node/1070168194",
      "properties": {
        "@id": "node/1070168194",
        "gns:dsg": "HLL",
        "is_in:country": "Indonesia",
        "is_in:country_code": "ID",
        "is_in:state": "Kalimantan Selatan",
        "name": "Gunung Sau",
        "natural": "peak",
        "note": "Modify date: 1998-04-27",
        "source": "NGA-GNS"
      },
      "geometry": {
        "type": "Point",
        "coordinates": [
          116.383333,
          -3.55
        ]
      }
    },
    {
      "type": "Feature",
      "id": "node/1070176698",
      "properties": {
        "@id": "node/1070176698",
        "gns:dsg": "HLL",
        "is_in:country": "Indonesia",
        "is_in:country_code": "ID",
        "name": "Gunung Saung",
        "natural": "peak",
        "note": "Modify date: 1994-01-29",
        "source": "NGA-GNS"
      },
      "geometry": {
        "type": "Point",
        "coordinates": [
          116.4,
          -3.583333
        ]
      }
    }
  ]
}